wikibasedataconnector/__init__.py
wikibasedataconnector/wikibasedataconnector.py
wikibasedataconnector-0.0.3.dist-info/LICENSE
wikibasedataconnector-0.0.3.dist-info/METADATA
wikibasedataconnector-0.0.3.dist-info/WHEEL
wikibasedataconnector-0.0.3.dist-info/top_level.txt
wikibasedataconnector-0.0.3.dist-info/RECORD
