Metadata-Version: 2.1
Name: wikibasedataconnector
Version: 0.0.3
Summary: Library used for mapping data easily into Wikibase Systems
Author-email: Xentity Corporation <contact@xentity.com>
Project-URL: Homepage, https://github.com/xentitycorporation/wikibasedataconnector
Project-URL: Bug Tracker, https://github.com/xentitycorporation/wikibasedataconnector/issues
Classifier: Programming Language :: Python :: 3
Classifier: License :: OSI Approved :: MIT License
Classifier: Operating System :: OS Independent
Requires-Python: >=3.7
License-File: LICENSE
Requires-Dist: requests (>=2.28.2)
Requires-Dist: wikitextparser (>=0.51.1)
Requires-Dist: pywikibot (==8.0.1)
